{
  "date": "20260223",
  "updated_at": "2026-02-23T21:55:43.743889",
  "industries": {
    "光電": {
      "buy": 345953.21,
      "sell": 122470.16,
      "net": 223483.05,
      "stock_count": 68
    },
    "金融保險": {
      "buy": 400950.95,
      "sell": 453655.7,
      "net": -52704.76,
      "stock_count": 32
    },
    "半導體": {
      "buy": 497797.65,
      "sell": 45379.27,
      "net": 452418.38,
      "stock_count": 93
    },
    "其他": {
      "buy": 145596.0,
      "sell": -31800.82,
      "net": 177396.82,
      "stock_count": 126
    },
    "塑膠工業": {
      "buy": 91552.57,
      "sell": 49541.16,
      "net": 42011.41,
      "stock_count": 21
    },
    "航運業": {
      "buy": 103334.28,
      "sell": 32907.22,
      "net": 70427.06,
      "stock_count": 27
    },
    "電子零組件": {
      "buy": 177017.95,
      "sell": 64185.86,
      "net": 112832.09,
      "stock_count": 102
    },
    "建材營造": {
      "buy": 24755.08,
      "sell": 24468.56,
      "net": 286.52,
      "stock_count": 55
    },
    "玻璃陶瓷": {
      "buy": 30395.0,
      "sell": 12194.29,
      "net": 18200.71,
      "stock_count": 5
    },
    "其他電子": {
      "buy": 79940.39,
      "sell": 25022.51,
      "net": 54917.88,
      "stock_count": 45
    },
    "通信網路": {
      "buy": 66157.32,
      "sell": 27816.59,
      "net": 38340.74,
      "stock_count": 43
    },
    "食品工業": {
      "buy": 12395.31,
      "sell": 14485.31,
      "net": -2089.99,
      "stock_count": 24
    },
    "化學工業": {
      "buy": 21154.75,
      "sell": 14905.4,
      "net": 6249.35,
      "stock_count": 28
    },
    "電子通路": {
      "buy": 25324.55,
      "sell": 16613.31,
      "net": 8711.24,
      "stock_count": 20
    },
    "電腦及週邊": {
      "buy": 180660.48,
      "sell": -18555.1,
      "net": 199215.58,
      "stock_count": 64
    },
    "油電燃氣": {
      "buy": 2776.03,
      "sell": 7301.84,
      "net": -4525.81,
      "stock_count": 8
    },
    "水泥工業": {
      "buy": 19634.14,
      "sell": 5130.99,
      "net": 14503.15,
      "stock_count": 7
    },
    "紡織纖維": {
      "buy": 17226.88,
      "sell": 6321.7,
      "net": 10905.17,
      "stock_count": 42
    },
    "電機機械": {
      "buy": 36570.5,
      "sell": 18362.2,
      "net": 18208.3,
      "stock_count": 49
    },
    "電器電纜": {
      "buy": 21848.48,
      "sell": 5828.71,
      "net": 16019.76,
      "stock_count": 16
    },
    "生技醫療": {
      "buy": 9558.95,
      "sell": 5220.56,
      "net": 4338.39,
      "stock_count": 56
    },
    "橡膠工業": {
      "buy": 16598.11,
      "sell": 9411.18,
      "net": 7186.94,
      "stock_count": 11
    },
    "鋼鐵工業": {
      "buy": 48854.5,
      "sell": -6042.5,
      "net": 54896.99,
      "stock_count": 31
    },
    "貿易百貨": {
      "buy": 5313.06,
      "sell": 2743.33,
      "net": 2569.73,
      "stock_count": 18
    },
    "資訊服務": {
      "buy": 2115.43,
      "sell": 1533.98,
      "net": 581.45,
      "stock_count": 11
    },
    "汽車工業": {
      "buy": 8434.72,
      "sell": 3775.01,
      "net": 4659.7,
      "stock_count": 42
    },
    "觀光餐旅": {
      "buy": 1583.18,
      "sell": 1734.18,
      "net": -151.0,
      "stock_count": 18
    },
    "造紙工業": {
      "buy": 3576.0,
      "sell": 577.06,
      "net": 2998.94,
      "stock_count": 7
    }
  }
}